Workbook
Name SegmentaçãodeDados_Cidade: #N/A

Sheet Projeto
A2: RADAR DE VENDAS: DO DADO À DECISÃO
A3: Excel • nível iniciante/intermediário • dados fictícios de 2025
A5: DESAFIO
A6: Contexto | B6: Você recebeu o registro de 360 vendas de uma pequena rede de cafés e presentes. A gerência quer entender o que vende, onde vende e como as vendas mudaram ao longo do ano.
A7: Objetivo | B7: Transformar a base em uma análise clara, calcular indicadores, responder às perguntas abaixo e recomendar uma ação comercial baseada nos dados.
A8: Tempo sugerido | B8: De 1 a 2 horas. Trabalhe nas abas Base de vendas e Minha análise; use esta aba como roteiro.
A10: ROTEIRO DE TRABALHO
A11: 1. Explore | B11: Confira os cabeçalhos, filtre e ordene os registros. Cada linha representa uma venda; os IDs são únicos. Verifique tipos de dados, células vazias e possíveis inconsistências.
A12: 2. Prepare | B12: A base já está formatada como Tabela do Excel. Não altere os dados originais. Complete as quatro colunas calculadas em amarelo na aba Base de vendas.
A13: 3. Receita bruta | B13: Na coluna Faturamento_bruto, calcule Quantidade × Preco_unitario. Exemplo de referência estruturada: =[@Quantidade]*[@Preco_unitario]
A14: 4. Desconto | B14: Na coluna Desconto, calcule Faturamento_bruto × Desconto_pct. Exemplo: =[@Faturamento_bruto]*[@Desconto_pct]
A15: 5. Receita líquida | B15: Na coluna Faturamento_liquido, calcule Faturamento_bruto − Desconto. Exemplo: =[@Faturamento_bruto]-[@Desconto]
A16: 6. Mês | B16: Na coluna Mes, transforme a Data no primeiro dia daquele mês (ex.: =DATA(ANO([@Data]);MÊS([@Data]);1)) e formate como mmm/aaaa. Assim, a ordem cronológica fica preservada.
A17: 7. Analise | B17: Crie Tabelas Dinâmicas para resumir as vendas por mês, produto/categoria e canal. Confira totais e use filtros ou segmentações para explorar a cidade.
A18: 8. Visualize | B18: Monte um painel com indicadores, um gráfico de linha para a evolução mensal e um gráfico de barras para comparar produtos ou canais.
A19: 9. Conclua | B19: Registre suas respostas na aba Minha análise. Escreva uma recomendação específica e cite os números que sustentam sua proposta.
A21: PERGUNTAS PARA INVESTIGAR
A22: 1 | B22: Como a receita líquida mudou mês a mês? Quais foram os meses mais fortes e mais fracos?
A23: 2 | B23: Quais produtos lideram em faturamento líquido e em unidades vendidas? O resultado é igual nas duas medidas?
A24: 3 | B24: Qual cidade gerou mais receita líquida? Há uma categoria ou produto que se destaque nela?
A25: 4 | B25: Como os canais de venda se comparam em faturamento e ticket médio?
A26: 5 | B26: O que acontece com a receita líquida quando o desconto aumenta? Compare os níveis de desconto e interprete com cuidado.
A27: 6 | B27: Que ação comercial você recomenda para o próximo período? Apoie a resposta com pelo menos dois números da análise.
A29: RECURSOS DO EXCEL PARA PRATICAR
A30: Tabela e filtros | B30: Explore a base sem perder a linha de cabeçalho; use filtros para selecionar cidade, produto, canal ou período.
A31: Fórmulas | B31: Use referências estruturadas para preencher as colunas calculadas. Para os indicadores, experimente SOMA, CONT.VALORES e divisão.
A32: Tabela Dinâmica | B32: Resuma a receita líquida, as unidades e a quantidade de vendas por diferentes dimensões.
A33: Gráficos | B33: Use linha para tendência mensal e barras para comparar categorias, produtos ou canais.
A34: Segmentação de dados | B34: Adicione filtros visuais por cidade ou canal ao painel, se sua versão do Excel oferecer esse recurso.
A35: Formatação condicional | B35: Destaque valores altos e baixos em uma tabela de comparação sem esconder os números.
A37: ENTREGA ESPERADA | B37: Um painel simples, três Tabelas Dinâmicas ou resumos equivalentes, respostas às seis perguntas e uma recomendação apoiada por dados.
A38: Checklist | B38: □ Colunas calculadas preenchidas □ Indicadores calculados □ Resumos por mês, produto e canal □ Gráficos legíveis □ Recomendação baseada em evidências
A39: Observação | B39: A base é fictícia e foi criada apenas para prática; não representa uma empresa real nem contém dados pessoais.

Sheet Base de vendas
A1: Base de prática • 360 vendas fictícias • janeiro a dezembro de 2025
A2: Uma linha = uma venda. As colunas calculadas à direita estão vazias de propósito; preencha-as seguindo a aba Projeto.
A4: ID_Venda | B4: Data | C4: Produto | D4: Categoria | E4: Cidade | F4: Canal | G4: Forma_pagamento | H4: Quantidade | I4: Preco_unitario | J4: Desconto_pct | K4: Faturamento_bruto | L4: Desconto | M4: Faturamento_liquido | N4: Mes | O4: Mes2
A5: V-2025-0025 | B5: 45658 | C5: Café tradicional 500g | D5: Café | E5: São Paulo | F5: Site | G5: Dinheiro | H5: 1 | I5: 28.9 | J5: 0.05 | K5: =H5*I5 -> 28.9 | L5: =K5*J5 -> 1.445 | M5: =K5-L5 -> 27.455 | N5: =VLOOKUP(Vendas[[#This Row],[Mes2]],Planilha1!$J:$K,2,FALSE) -> #N/A | O5: 01/1/2025
A6: V-2025-0026 | B6: 45658 | C6: Filtro de papel (100 un.) | D6: Acessórios | E6: Campinas | F6: Aplicativo | G6: Cartão de crédito | H6: 1 | I6: 12.9 | J6: 0.05 | K6: =H6*I6 -> 12.9 | L6: =K6*J6 -> 0.645 | M6: =K6-L6 -> 12.255 | N6: =VLOOKUP(Vendas[[#This Row],[Mes2]],Planilha1!$J:$K,2,FALSE) -> #N/A | O6: 01/1/2025
A7: V-2025-0006 | B7: 45659 | C7: Garrafa térmica | D7: Acessórios | E7: Curitiba | F7: Site | G7: Cartão de débito | H7: 2 | I7: 89.9 | J7: 0.1 | K7: =H7*I7 -> 179.8 | L7: =K7*J7 -> 17.98 | M7: =K7-L7 -> 161.82 | N7: =VLOOKUP(Vendas[[#This Row],[Mes2]],Planilha1!$J:$K,2,FALSE) -> #N/A | O7: 01/1/2025
A8: V-2025-0007 | B8: 45659 | C8: Café especial 250g | D8: Café | E8: São Paulo | F8: Loja física | G8: Cartão de débito | H8: 2 | I8: 39.9 | J8: 0.1 | K8: =H8*I8 -> 79.8 | L8: =K8*J8 -> 7.98 | M8: =K8-L8 -> 71.82 | N8: =VLOOKUP(Vendas[[#This Row],[Mes2]],Planilha1!$J:$K,2,FALSE) -> #N/A | O8: 01/1/2025
A9: V-2025-0029 | B9: 45659 | C9: Kit presente | D9: Presentes | E9: Curitiba | F9: Aplicativo | G9: Cartão de crédito | H9: 1 | I9: 74.9 | J9: 0 | K9: =H9*I9 -> 74.9 | L9: =K9*J9 -> 0 | M9: =K9-L9 -> 74.9 | N9: =VLOOKUP(Vendas[[#This Row],[Mes2]],Planilha1!$J:$K,2,FALSE) -> #N/A | O9: 01/1/2025
A10: V-2025-0005 | B10: 45664 | C10: Chocolate 70% | D10: Presentes | E10: Rio de Janeiro | F10: Loja física | G10: Cartão de débito | H10: 3 | I10: 18.9 | J10: 0 | K10: =H10*I10 -> 56.7 | L10: =K10*J10 -> 0 | M10: =K10-L10 -> 56.7 | N10: =VLOOKUP(Vendas[[#This Row],[Mes2]],Planilha1!$J:$K,2,FALSE) -> #N/A | O10: 01/1/2025
A11: V-2025-0012 | B11: 45664 | C11: Chocolate 70% | D11: Presentes | E11: São Paulo | F11: Aplicativo | G11: Cartão de débito | H11: 1 | I11: 18.9 | J11: 0.15 | K11: =H11*I11 -> 18.9 | L11: =K11*J11 -> 2.835 | M11: =K11-L11 -> 16.065 | N11: =VLOOKUP(Vendas[[#This Row],[Mes2]],Planilha1!$J:$K,2,FALSE) -> #N/A | O11: 01/1/2025
A12: V-2025-0004 | B12: 45665 | C12: Café tradicional 500g | D12: Café | E12: Curitiba | F12: Site | G12: Pix | H12: 3 | I12: 28.9 | J12: 0 | K12: =H12*I12 -> 86.7 | L12: =K12*J12 -> 0 | M12: =K12-L12 -> 86.7 | N12: =VLOOKUP(Vendas[[#This Row],[Mes2]],Planilha1!$J:$K,2,FALSE) -> #N/A | O12: 01/1/2025
A13: V-2025-0003 | B13: 45668 | C13: Café especial 250g | D13: Café | E13: Campinas | F13: Site | G13: Cartão de crédito | H13: 3 | I13: 39.9 | J13: 0.1 | K13: =H13*I13 -> 119.7 | L13: =K13*J13 -> 11.97 | M13: =K13-L13 -> 107.73 | N13: =VLOOKUP(Vendas[[#This Row],[Mes2]],Planilha1!$J:$K,2,FALSE) -> #N/A | O13: 01/1/2025
A14: V-2025-0013 | B14: 45669 | C14: Garrafa térmica | D14: Acessórios | E14: São Paulo | F14: Loja física | G14: Pix | H14: 1 | I14: 89.9 | J14: 0 | K14: =H14*I14 -> 89.9 | L14: =K14*J14 -> 0 | M14: =K14-L14 -> 89.9 | N14: =VLOOKUP(Vendas[[#This Row],[Mes2]],Planilha1!$J:$K,2,FALSE) -> #N/A | O14: 01/1/2025
A15: V-2025-0022 | B15: 45670 | C15: Café especial 250g | D15: Café | E15: Rio de Janeiro | F15: Site | G15: Cartão de débito | H15: 1 | I15: 39.9 | J15: 0.05 | K15: =H15*I15 -> 39.9 | L15: =K15*J15 -> 1.995 | M15: =K15-L15 -> 37.905 | N15: =VLOOKUP(Vendas[[#This Row],[Mes2]],Planilha1!$J:$K,2,FALSE) -> #N/A | O15: 01/1/2025
A16: V-2025-0028 | B16: 45671 | C16: Café tradicional 500g | D16: Café | E16: Santos | F16: Loja física | G16: Dinheiro | H16: 2 | I16: 28.9 | J16: 0.15 | K16: =H16*I16 -> 57.8 | L16: =K16*J16 -> 8.67 | M16: =K16-L16 -> 49.13 | N16: =VLOOKUP(Vendas[[#This Row],[Mes2]],Planilha1!$J:$K,2,FALSE) -> #N/A | O16: 01/1/2025
... A364: V-2025-0360 | B364: 46020 | C364: Caneca artesanal | D364: Acessórios | E364: Campinas | F364: Loja física | G364: Pix | H364: 3 | I364: 34.9 | J364: 0.1 | K364: =H364*I364 -> 104.7 | L364: =K364*J364 -> 10.47 | M364: =K364-L364 -> 94.23 | N364: =VLOOKUP(Vendas[[#This Row],[Mes2]],Planilha1!$J:$K,2,FALSE) -> #N/A | O364: 01/12/2025
H365: =SUM(H5:H364) -> 693 | I365: =SUM(I5:I364) -> 15096 | K365: R$ 27.605,70 | L365: =SUM(L5:L364) -> 1780.39 | M365: R$ 25.825,31
M366: =MEDIAN(M5:M364) -> 59.33

Sheet Minha análise
A2: MINHA ANÁLISE
A3: Preencha as células amarelas depois de preparar a base e montar seus resumos no Excel.
A5: INDICADORES | B5: Como calcular | C5: Meu resultado | D5: O que esse número mostra?
A6: Faturamento bruto: 27.605,70 | B6: Soma de Quantidade × Preco_unitario | C6: Unidades vendidas (693): | D6: mostra o volume total de produtos comercializados, indicando a força da demanda.
A7: Descontos concedidos: 1.780,39 | B7: Soma da coluna Desconto | C7: Número de vendas (360): | D7: revela quantas transações ocorreram, útil para entender frequência de compra.
A8: Faturamento líquido: 25.825,31 | B8: Faturamento bruto − descontos | C8: Ticket médio (71,74): | D8: demonstra quanto, em média, cada cliente gastou por compra — um reflexo direto da estratégia de preços e mix de produtos.
A9: Unidades vendidas: 693 | B9: Soma de Quantidade
A10: Número de vendas: 360 | B10: Contagem de ID_Venda
A11: Ticket médio: 71,74 | B11: Faturamento líquido ÷ número de vendas
A14: PERGUNTA | B14: Minha resposta / evidência
A15: Tendência mensal: meses mais fortes/fracos e comportamento ao longo do ano | B15: ticket medio mensal foi de 2.152,11 - o mês mas fraco foi maio com 1.702 ,90 e o mês mais forte foi dezmbro 2.896,19
A16: Produtos: líderes por faturamento líquido e por unidades | B16: produto que mais vendeu por unidade café especial, produto que mais vendeu por faturamento liquido café especia
A17: Cidade: maior receita e destaque de produto/categoria | B17: a cidade que mais vendeu foi São paulo, e a categoria que mais se destacou foi café com café especial saIindo na frente
A18: Canal: comparação de receita e ticket médio | B18: a receita do loja fisica: 12.907,84 e ticket medio 1.075,65 a receita do site: 8.460,55 e ticket medio 705,05, a receita do aplicativo: 4.456,93e ticket medio 371,41
A19: Descontos: comparação entre níveis e efeito observado | B19: faturamento liquido total 25.825,31 desconto total 1.780,39
A20: Recomendação: ação proposta e números que a sustentam | B20: Plano de Ação 1. Expandir oferta de café especial, 2. Fortalecer presença digital (site e aplicativo), 3. Aproveitar sazonalidade de fim de ano, 4. Gestão de descontos controlada

Sheet Planilha1
C1: RELATORIO RADAR DE VENDAS
C3: FATURAMENTO POR PRODUTO | I3: FATURAMENTO POR MÊS
C4: Cidade | D4: Santos | I4: Cidade | J4: Santos
C6: Soma de Faturamento_liquido | D6: Rótulos de Coluna | I6: Rótulos de Linha | J6: Soma de Faturamento_liquido
C7: Rótulos de Linha | D7: Aplicativo | E7: Loja física | F7: Site | G7: Total Geral | I7: 45658 | J7: 169.4 | O7: DE
C8: Café | I8: 45659 | J8: 213.62 | O8: 01/1/2025 | P8: PARA
C9: Café especial 250g | D9: 113.715 | E9: 107.73 | F9: 381.045 | G9: 602.49 | I9: 45660 | J9: 156.62 | O9: 01/2/2025 | P9: 45658
C10: Café tradicional 500g | D10: 78.03 | E10: 244.205 | F10: 134.385 | G10: 456.62 | I10: 45661 | J10: 250.48 | O10: 01/3/2025 | P10: 45659
C11: Café em grãos 1kg | D11: 71.91 | E11: 303.62 | G11: 375.53 | I11: 45662 | J11: 162.95 | O11: 01/4/2025 | P11: 45660
C12: Acessórios | I12: 45663 | J12: 325.125 | O12: 01/5/2025 | P12: 45661
C13: Garrafa térmica | E13: 418.035 | F13: 341.62 | G13: 759.655 | I13: 45664 | J13: 80.92 | O13: 01/6/2025 | P13: 45662
C14: Filtro de papel (100 un.) | E14: 32.895 | F14: 10.965 | G14: 43.86 | I14: 45665 | J14: 273.225 | O14: 01/7/2025 | P14: 45663
C15: Presentes | I15: 45666 | J15: 96.6 | O15: 01/8/2025 | P15: 45664
C16: Chocolate 70% | D16: 113.4 | E16: 146.475 | F16: 17.01 | G16: 276.885 | I16: 45667 | J16: 171.515 | O16: 01/9/2025 | P16: 45665
C17: Kit presente | D17: 74.9 | G17: 74.9 | I17: 45668 | J17: 79.8 | O17: 01/10/2025 | P17: 45666
C18: Total Geral | D18: 451.955 | E18: 1252.96 | F18: 885.025 | G18: 2589.94 | I18: 45669 | J18: 609.685 | O18: 01/11/2025 | P18: 45667
I19: Total Geral | J19: 2589.94 | O19: 01/12/2025 | P19: 45668
P20: 45669
C21: QUANTIDADDE DE PRODUTOS VENDIDOS | F21: Produto que mais vendeu | I21: FATURAMENTO POR CANAL
C22: Cidade | D22: Santos | F22: Produto | G22: Quantidade | I22: Rótulos de Linha | J22: Soma de Faturamento_liquido | K22: ticket medio
F23: =C25 -> Café tradicional 500g | G23: =GETPIVOTDATA("[Measures].[Soma de Quantidade]",$C$24,"[Vendas].[Produto]","[Vendas].[Produto].&[Café especial 250g]") -> 16 | I23: Loja física | J23: 1252.96 | K23: 66.24
C24: Rótulos de Linha | D24: Soma de Quantidade | I24: Site | J24: 885.025 | K24: 76.22
C25: Café tradicional 500g | D25: 17 | I25: Aplicativo | J25: 451.955 | K25: 81.04
C26: Café especial 250g | D26: 16 | F26: Produto Que menos Vendeu | I26: Total Geral | J26: 2589.94
C27: Chocolate 70% | D27: 15 | F27: Produto | G27: Quantidade
C28: Garrafa térmica | D28: 9 | F28: =C32 -> Total Geral | G28: =GETPIVOTDATA("[Measures].[Soma de Quantidade]",$C$24,"[Vendas].[Produto]","[Vendas].[Produto].&[Garrafa térmica]") -> 9
C29: Café em grãos 1kg | D29: 5
C30: Filtro de papel (100 un.) | D30: 4
C31: Kit presente | D31: 1
C32: Total Geral | D32: 67

Sheet Planilha2
C1: GRAFICOS RADAR DE VENDAS
